{
  "db_name": "PostgreSQL",
  "query": "\n            SELECT jsonb_build_object(\n                'type', 'Feature',\n                'id', id,\n                'geometry', ST_AsGeoJSON(ST_Transform(geom, 4326))::jsonb,\n                'properties', properties || jsonb_build_object('name', name)\n            ) as feature\n            FROM app.features\n            WHERE collection_id = $1 AND status = 'ACTIVE'\n            ORDER BY id\n            LIMIT $2\n            ",
  "describe": {
    "columns": [
      {
        "ordinal": 0,
        "name": "feature",
        "type_info": "Jsonb"
      }
    ],
    "parameters": {
      "Left": [
        "Int4",
        "Int8"
      ]
    },
    "nullable": [
      null
    ]
  },
  "hash": "b19689f80c826f7f9ba3735b3549c29e6f5e5ccf47a8ebf095a1cc6cb537ead9"
}
